mojiweather_api/__init__.py
mojiweather_api/config.py
mojiweather_api/exceptions.py
mojiweather_api/html_scraper.py
mojiweather_api/json_client.py
mojiweather_api/logger.py
mojiweather_api/models.py
mojiweather_api/services.py
mojiweather_api-0.1.1.dist-info/licenses/LICENSE
mojiweather_api-0.1.1.dist-info/METADATA
mojiweather_api-0.1.1.dist-info/WHEEL
mojiweather_api-0.1.1.dist-info/top_level.txt
mojiweather_api-0.1.1.dist-info/RECORD
