Metadata-Version: 2.4
Name: mojiweather-api
Version: 0.1.1
Summary: A Python package to access weather data from Moji Weather (unofficial scraping).
Author-email: VerNe <yuu_seeing@foxmail.com>
License: MIT License
Project-URL: Homepage, https://github.com/ID-VerNe/mojiweather_api
Keywords: mojiweather,weather,api,scraping,asynchronous
Classifier: Programming Language :: Python :: 3
Classifier: License :: OSI Approved :: MIT License
Classifier: Operating System :: OS Independent
Classifier: Intended Audience :: Developers
Classifier: Topic :: Internet :: WWW/HTTP :: Indexing/Search
Classifier: Topic :: Software Development :: Libraries :: Python Modules
Classifier: Topic :: Scientific/Engineering :: Atmospheric Science
Requires-Python: >=3.7
License-File: LICENSE
Requires-Dist: httpx>=0.20.0
Requires-Dist: beautifulsoup4>=4.10.0
Dynamic: license-file
